Calculator/Calculator.py
Calculator/MathOperators.py
Calculator/MathSegmentClass.py
Calculator/MathTerm.py
Calculator/__init__.py
EasyTeleBot/BotAction.py
EasyTeleBot/Chat.py
EasyTeleBot/GenericFunctions.py
EasyTeleBot/TelegramBot.py
EasyTeleBot/__init__.py
EasyTeleBot/BotActionLib/ActionType.py
EasyTeleBot/BotActionLib/BotActionClass.py
EasyTeleBot/BotActionLib/BotCommands.py
EasyTeleBot/BotActionLib/BotResponses.py
EasyTeleBot/BotActionLib/MarkupType.py
EasyTeleBot/BotActionLib/__init__.py
EasyTeleBot/DatabaseLib/ChatDB.py
EasyTeleBot/DatabaseLib/__init__.py
EasyTeleBot/DatabaseLib/pandasDB.py
EasyTeleBot-0.0.4.dist-info/LICENSE
EasyTeleBot-0.0.4.dist-info/METADATA
EasyTeleBot-0.0.4.dist-info/WHEEL
EasyTeleBot-0.0.4.dist-info/top_level.txt
EasyTeleBot-0.0.4.dist-info/RECORD
