Metadata-Version: 2.1
Name: EasyTeleBot
Version: 0.0.4
Summary: Configurable Telegram Bot package
Home-page: https://github.com/idozahavy/EasyTeleBot
Author: Ido Zahavy
Author-email: idozahavy@gmail.com
License: UNKNOWN
Platform: UNKNOWN
Classifier: Development Status :: 3 - Alpha
Classifier: Programming Language :: Python :: 3
Classifier: License :: OSI Approved :: MIT License
Classifier: Operating System :: OS Independent
Requires-Python: >=3.6
Requires-Dist: flask
Requires-Dist: python-telegram-bot
Requires-Dist: pandas
Requires-Dist: numpy
Requires-Dist: StringCalculator
